kindsealion/__init__.py
kindsealion/__main__.py
kindsealion/main2.py
kindsealion/parse_args.py
kindsealion/templates/Taskfile.yml.j2
kindsealion/templates/base.j2
kindsealion/templates/dns.sh.j2
kindsealion/templates/extended.j2
kindsealion/templates/ringgem.sh.j2
kindsealion/templates/script.sh.j2
kindsealion/templates/ubuntu.pkr.hcl
kindsealion-0.1.6.dist-info/METADATA
kindsealion-0.1.6.dist-info/WHEEL
kindsealion-0.1.6.dist-info/entry_points.txt
kindsealion-0.1.6.dist-info/RECORD
