Metadata-Version: 2.4
Name: kindsealion
Version: 0.1.6
Summary: Add your description here
Author-email: Taylor Monacelli <taylormonacelli@gmail.com>
Requires-Python: >=3.8
Requires-Dist: jinja2>=3.1.3
Requires-Dist: networkx>=3.1
Requires-Dist: ruamel-yaml>=0.18.6
